kws_decoder/__init__.py
kws_decoder/kws_decoder.cpython-310-i386-linux-gnu.so
kws_decoder/kws_decoder.cpython-311-i386-linux-gnu.so
kws_decoder/kws_decoder.cpython-312-i386-linux-gnu.so
kws_decoder/kws_decoder.cpython-313-i386-linux-gnu.so
kws_decoder/kws_decoder.cpython-39-i386-linux-gnu.so
kws_decoder/kws_decoder.pypy39-pp73-x86-linux-gnu.so
kws_decoder-0.1.3.dist-info/METADATA
kws_decoder-0.1.3.dist-info/WHEEL
kws_decoder-0.1.3.dist-info/RECORD
kws_decoder-0.1.3.dist-info/licenses/LICENSE
