Metadata-Version: 2.2
Name: kws-decoder
Version: 0.1.3
Summary: Keyword spotting decoder built with PyBind11
Author-Email: Mohammad Hassan Sohan Ajini <mohamad.hasan.sohan.ajini@gmail.com>, Navid Naderi <navid.nadery@gmail.com>
License: MIT
Classifier: Intended Audience :: Developers
Classifier: Intended Audience :: Science/Research
Classifier: Programming Language :: Python :: 3.9
Classifier: Programming Language :: Python :: 3.10
Classifier: Programming Language :: Python :: 3.11
Classifier: Programming Language :: Python :: 3.12
Classifier: Programming Language :: Python :: 3.13
Classifier: Topic :: Scientific/Engineering :: Artificial Intelligence
Classifier: Topic :: Multimedia :: Sound/Audio
Classifier: Topic :: Multimedia :: Sound/Audio :: Analysis
Classifier: Topic :: Multimedia :: Sound/Audio :: Speech
Project-URL: Homepage, https://github.com/mohamad-hasan-sohan-ajini/kws-decoder
Project-URL: Repository, https://github.com/mohamad-hasan-sohan-ajini/kws-decoder
Project-URL: Issues, https://github.com/mohamad-hasan-sohan-ajini/kws-decoder/issues
Requires-Python: >=3.9
Provides-Extra: test
Requires-Dist: pytest; extra == "test"
Provides-Extra: ext
Requires-Dist: pygtrie; extra == "ext"
Requires-Dist: torch; extra == "ext"
Requires-Dist: tqdm; extra == "ext"
